apistrap/__init__.py
apistrap/aiohttp.py
apistrap/decorators.py
apistrap/errors.py
apistrap/examples.py
apistrap/extension.py
apistrap/flask.py
apistrap/operation_wrapper.py
apistrap/schemas.py
apistrap/schematics_converters.py
apistrap/tags.py
apistrap/types.py
apistrap/utils.py
apistrap/templates/apidocs.html
apistrap/templates/redoc.html
apistrap-0.10.0.dist-info/LICENSE
apistrap-0.10.0.dist-info/METADATA
apistrap-0.10.0.dist-info/WHEEL
apistrap-0.10.0.dist-info/top_level.txt
apistrap-0.10.0.dist-info/RECORD
