Metadata-Version: 2.1
Name: apistrap
Version: 0.10.0
Summary: Iterait REST API utilities
Home-page: https://github.com/iterait/apistrap
Author: ['Iterait a.s.', 'Cognexa Solutions s.r.o.']
Author-email: hello@iterait.com
License: MIT
Keywords: api rest http
Platform: UNKNOWN
Classifier: Development Status :: 4 - Beta
Classifier: Environment :: Console
Classifier: Intended Audience :: Developers
Classifier: Operating System :: Unix
Classifier: Programming Language :: Python :: Implementation :: CPython
Classifier: License :: OSI Approved :: MIT License
Classifier: Programming Language :: Python :: 3.7
Requires-Dist: apispec (==1.2)
Requires-Dist: pydantic
Requires-Dist: more-itertools
Requires-Dist: Werkzeug
Requires-Dist: jinja2
Requires-Dist: docstring-parser (>=0.5)
Requires-Dist: markupsafe (<2.0.0)
Provides-Extra: aiohttp
Requires-Dist: aiohttp (<4.0.0) ; extra == 'aiohttp'
Provides-Extra: flask
Requires-Dist: flask (<=1.1.4) ; extra == 'flask'
